{
  "vocab": {
    "<PAD>": 0,
    "<UNK>": 1,
    " ": 2,
    "#": 3,
    "'": 4,
    ",": 5,
    "-": 6,
    ".": 7,
    "/": 8,
    "0": 9,
    "1": 10,
    "2": 11,
    "3": 12,
    "4": 13,
    "5": 14,
    "6": 15,
    "7": 16,
    "8": 17,
    "9": 18,
    ":": 19,
    "=": 20,
    "?": 21,
    "@": 22,
    "A": 23,
    "B": 24,
    "C": 25,
    "D": 26,
    "E": 27,
    "F": 28,
    "G": 29,
    "H": 30,
    "I": 31,
    "J": 32,
    "K": 33,
    "L": 34,
    "M": 35,
    "N": 36,
    "O": 37,
    "P": 38,
    "Q": 39,
    "R": 40,
    "S": 41,
    "T": 42,
    "U": 43,
    "V": 44,
    "W": 45,
    "Y": 46,
    "_": 47,
    "a": 48,
    "b": 49,
    "c": 50,
    "d": 51,
    "e": 52,
    "f": 53,
    "g": 54,
    "h": 55,
    "i": 56,
    "j": 57,
    "k": 58,
    "l": 59,
    "m": 60,
    "n": 61,
    "o": 62,
    "p": 63,
    "q": 64,
    "r": 65,
    "s": 66,
    "t": 67,
    "u": 68,
    "v": 69,
    "w": 70,
    "x": 71,
    "y": 72,
    "z": 73
  },
  "label2id": {
    "O": 0,
    "B-URL": 1,
    "I-URL": 2,
    "B-ATTRIB_NAME": 3,
    "I-ATTRIB_NAME": 4,
    "B-FIELD_ID": 5,
    "I-FIELD_ID": 6,
    "B-FIELD_VALUE": 7,
    "I-FIELD_VALUE": 8,
    "B-ENV_VALUE": 9,
    "I-ENV_VALUE": 10,
    "B-CLICK_ATTRIB_NAME": 11,
    "I-CLICK_ATTRIB_NAME": 12,
    "B-CLICK_ID": 13,
    "I-CLICK_ID": 14,
    "B-ELEMENT_TAG": 15,
    "I-ELEMENT_TAG": 16
  },
  "id2label": {
    "0": "O",
    "1": "B-URL",
    "2": "I-URL",
    "3": "B-ATTRIB_NAME",
    "4": "I-ATTRIB_NAME",
    "5": "B-FIELD_ID",
    "6": "I-FIELD_ID",
    "7": "B-FIELD_VALUE",
    "8": "I-FIELD_VALUE",
    "9": "B-ENV_VALUE",
    "10": "I-ENV_VALUE",
    "11": "B-CLICK_ATTRIB_NAME",
    "12": "I-CLICK_ATTRIB_NAME",
    "13": "B-CLICK_ID",
    "14": "I-CLICK_ID",
    "15": "B-ELEMENT_TAG",
    "16": "I-ELEMENT_TAG"
  },
  "intent2id": {
    "find_tag_text_compare": 0,
    "navigate_click_by_id": 1,
    "navigate_fill_fields": 2,
    "navigate_fill_fields_click": 3,
    "navigate_only": 4
  },
  "id2intent": {
    "0": "find_tag_text_compare",
    "1": "navigate_click_by_id",
    "2": "navigate_fill_fields",
    "3": "navigate_fill_fields_click",
    "4": "navigate_only"
  },
  "templates": {
    "navigate_only": {
      "test_name": "Navigation Test",
      "base_url": "__URL__",
      "steps": [
        {
          "step_no": "__AUTO_STEP_NO__",
          "action": "navigate",
          "element": null,
          "by": null,
          "selector": null,
          "value": "__URL__",
          "value_from_env": null,
          "description": "Navigate to the application URL"
        }
      ]
    },
    "navigate_fill_fields": {
      "test_name": "Dynamic Attribute Input Test",
      "base_url": "__URL__",
      "steps": [
        {
          "step_no": "__AUTO_STEP_NO__",
          "action": "navigate",
          "element": null,
          "by": null,
          "selector": null,
          "value": "__URL__",
          "value_from_env": null,
          "description": "Navigate to the application URL"
        },
        {
          "repeat_for": "__FIELDS__",
          "template": {
            "step_no": "__AUTO_STEP_NO__",
            "action": "type",
            "element": "__FIELD_ID__",
            "attribute_name": "__ATTRIB_NAME__",
            "by": "css selector",
            "selector": "input[__ATTRIB_NAME__='__FIELD_ID__']",
            "value": "__FIELD_VALUE__",
            "value_from_env": "__ENV_VALUE__",
            "description": "Enter value into input using dynamic attribute selector"
          }
        }
      ]
    },
    "navigate_fill_fields_click": {
      "test_name": "Dynamic Attribute Form Submit Test",
      "base_url": "__URL__",
      "steps": [
        {
          "step_no": "__AUTO_STEP_NO__",
          "action": "navigate",
          "element": null,
          "by": null,
          "selector": null,
          "value": "__URL__",
          "value_from_env": null,
          "description": "Navigate to the application URL"
        },
        {
          "repeat_for": "__FIELDS__",
          "template": {
            "step_no": "__AUTO_STEP_NO__",
            "action": "type",
            "element": "__FIELD_ID__",
            "attribute_name": "__ATTRIB_NAME__",
            "by": "css selector",
            "selector": "input[__ATTRIB_NAME__='__FIELD_ID__']",
            "value": "__FIELD_VALUE__",
            "value_from_env": "__ENV_VALUE__",
            "description": "Enter value into input using dynamic attribute selector"
          }
        },
        {
          "step_no": "__AUTO_STEP_NO__",
          "action": "click",
          "element": "submit button",
          "by": "css selector",
          "selector": "button[type='submit']",
          "value": null,
          "value_from_env": null,
          "description": "Click the submit button"
        }
      ]
    },
    "navigate_click_by_id": {
      "test_name": "Dynamic Attribute Click Test",
      "base_url": "__URL__",
      "steps": [
        {
          "step_no": "__AUTO_STEP_NO__",
          "action": "navigate",
          "element": null,
          "by": null,
          "selector": null,
          "value": "__URL__",
          "value_from_env": null,
          "description": "Navigate to the application URL"
        },
        {
          "step_no": "__AUTO_STEP_NO__",
          "action": "click",
          "element": "click target",
          "attribute_name": "__CLICK_ATTRIB_NAME__",
          "by": "css selector",
          "selector": "[__CLICK_ATTRIB_NAME__='__CLICK_ID__']",
          "value": null,
          "value_from_env": null,
          "description": "Click the element using dynamic attribute selector"
        }
      ]
    },
    "find_tag_text_compare": {
      "test_name": "Dynamic Tag Text Compare Test",
      "base_url": "__URL__",
      "steps": [
        {
          "step_no": "__AUTO_STEP_NO__",
          "action": "assert_text",
          "element": "__TEXT_TAG__",
          "tag_name": "__TEXT_TAG__",
          "attribute_name": "__TEXT_ATTRIB_NAME__",
          "by": "css selector",
          "selector": "__TEXT_TAG__[__TEXT_ATTRIB_NAME__='__TEXT_FIELD_ID__']",
          "value": "__TEXT_VALUE__",
          "value_from_env": null,
          "description": "Find the dynamic tag by attribute and compare its text value"
        }
      ]
    }
  },
  "max_len": 700,
  "model_args": {
    "vocab_size": 74,
    "n_labels": 17,
    "n_intents": 5,
    "emb_dim": 96,
    "hidden_dim": 160,
    "num_layers": 2,
    "dropout": 0.25
  }
}